petljadoc/__init__.py
petljadoc/__main__.py
petljadoc/cli.py
petljadoc/course.py
petljadoc/cyr2lat.py
petljadoc/package.py
petljadoc/petlja_builder.py
petljadoc/templateutil.py
petljadoc/util.py
petljadoc/nb-templates/classic2/index.html.j2
petljadoc/nb-templates/classic2/base/base.html.j2
petljadoc/nb-templates/classic2/base/celltags.j2
petljadoc/nb-templates/classic2/base/display_priority.j2
petljadoc/nb-templates/classic2/base/jupyter_widgets.html.j2
petljadoc/nb-templates/classic2/base/mathjax.html.j2
petljadoc/nb-templates/classic2/base/null.j2
petljadoc/nbtemplates/classic2/index.html.j2
petljadoc/nbtemplates/classic2/base/base.html.j2
petljadoc/nbtemplates/classic2/base/celltags.j2
petljadoc/nbtemplates/classic2/base/display_priority.j2
petljadoc/nbtemplates/classic2/base/jupyter_widgets.html.j2
petljadoc/nbtemplates/classic2/base/mathjax.html.j2
petljadoc/nbtemplates/classic2/base/null.j2
petljadoc/project-templates/course/.t.gitignore
petljadoc/project-templates/course/conf-petljadoc.t.json
petljadoc/project-templates/course/conf.t.py
petljadoc/project-templates/course/package-conf.json
petljadoc/project-templates/course/pavement.t.py
petljadoc/project-templates/course/template_settings.t.json
petljadoc/project-templates/course/_images/.gitkeep
petljadoc/project-templates/course/_includes/.gitkeep
petljadoc/project-templates/course/_sources/index.t.yaml
petljadoc/project-templates/course/_sources/index.yaml
petljadoc/project-templates/course/_sources/1_Lesson/intro.rst
petljadoc/project-templates/course/_sources/1_Lesson/quiz.rst
petljadoc/project-templates/course/_static/.gitkeep
petljadoc/project-templates/runestone/.t.gitignore
petljadoc/project-templates/runestone/conf-petljadoc.t.json
petljadoc/project-templates/runestone/conf.t.py
petljadoc/project-templates/runestone/pavement.t.py
petljadoc/project-templates/runestone/_images/.gitkeep
petljadoc/project-templates/runestone/_includes/.gitkeep
petljadoc-1.4.8.dist-info/licenses/LICENSE
petljadoc-1.4.8.dist-info/METADATA
petljadoc-1.4.8.dist-info/WHEEL
petljadoc-1.4.8.dist-info/entry_points.txt
petljadoc-1.4.8.dist-info/top_level.txt
petljadoc-1.4.8.dist-info/RECORD
