Metadata-Version: 2.4
Name: petljadoc
Version: 1.4.8
Summary: Petlja's command-line interface for learning content
Home-page: https://github.com/Petlja/PetljaDoc
Author: Fondacija Petlja
Author-email: team@petlja.org
Classifier: Programming Language :: Python :: 3.6
Classifier: License :: OSI Approved :: MIT License
Classifier: Operating System :: OS Independent
Classifier: Topic :: Education
Classifier: Topic :: Text Processing :: Markup
Requires-Python: >=3.7
License-File: LICENSE
Requires-Dist: docutils>=0.16
Requires-Dist: sphinx==5.3.0
Requires-Dist: paver>=1.3
Requires-Dist: runestone-petljadoc>=3.1.2.8
Requires-Dist: click>=7.0
Requires-Dist: cyrtranslit>=0.4
Requires-Dist: colorama>=0.4.1
Requires-Dist: pyyaml>=5
Requires-Dist: watchdog>=0.10
Requires-Dist: livereload>=2.6.3
Requires-Dist: nbconvert>=6.1.0
Requires-Dist: lxml
Requires-Dist: jinja2<3.1,>=3.0
Requires-Dist: setuptools
Dynamic: author
Dynamic: author-email
Dynamic: classifier
Dynamic: description
Dynamic: description-content-type
Dynamic: home-page
Dynamic: license-file
Dynamic: requires-dist
Dynamic: requires-python
Dynamic: summary
